serpyco_rs-1.17.0.dist-info/METADATA
serpyco_rs-1.17.0.dist-info/WHEEL
serpyco_rs-1.17.0.dist-info/licenses/LICENSE
serpyco_rs/__init__.py
serpyco_rs/_custom_types.py
serpyco_rs/_describe.py
serpyco_rs/_impl.py
serpyco_rs/_impl.pyi
serpyco_rs/_json_schema/__init__.py
serpyco_rs/_json_schema/_consts.py
serpyco_rs/_json_schema/_convert.py
serpyco_rs/_json_schema/_entities.py
serpyco_rs/_main.py
serpyco_rs/_meta.py
serpyco_rs/_secial_forms.py
serpyco_rs/_serpyco_rs.cpython-313-arm-linux-gnueabihf.so
serpyco_rs/_type_utils.py
serpyco_rs/_utils.py
serpyco_rs/exceptions.py
serpyco_rs/metadata.py
serpyco_rs/py.typed
serpyco_rs-1.17.0.dist-info/RECORD
